{"generation": [{"1": {"category": "b", "trial": 1, "stimulus": 29, "rt": 1972}, "0": {"category": "b", "trial": 0, "stimulus": 57, "rt": 1449}, "3": {"category": "b", "trial": 3, "stimulus": 28, "rt": 1603}, "2": {"category": "b", "trial": 2, "stimulus": 33, "rt": 1468}, "5": {"category": "b", "trial": 5, "stimulus": 64, "rt": 4004}, "4": {"category": "b", "trial": 4, "stimulus": 12, "rt": 2823}, "7": {"category": "b", "trial": 7, "stimulus": 34, "rt": 1651}, "6": {"category": "b", "trial": 6, "stimulus": 10, "rt": 2184}}, {}], "info": {"sessionorder": "b-bc", "participant": 16, "exposed": true, "lab": true, "start": 1534196497818, "counterbalance": 7, "condition": "Middle", "browser": {"platform": "MacIntel", "userAgent": "Mozilla/5.0 (Macintosh; Intel Mac OS X 10.13; rv:61.0) Gecko/20100101 Firefox/61.0"}}, "experiment": {"Paradigm": "TACL", "Stimuli": "Size-Color Squares", "Experiment": "Generating-Multiple-Categories"}, "observation": [{"1": {"stimulus": 32, "trial": 1, "rt": 734}, "0": {"stimulus": 30, "trial": 0, "rt": 1136}, "3": {"stimulus": 50, "trial": 3, "rt": 761}, "2": {"stimulus": 48, "trial": 2, "rt": 801}}, {"1": {"stimulus": 50, "trial": 1, "rt": 852}, "0": {"stimulus": 48, "trial": 0, "rt": 971}, "3": {"stimulus": 32, "trial": 3, "rt": 888}, "2": {"stimulus": 30, "trial": 2, "rt": 876}}], "generalization": [{}, {}]}